experiment1_light/light.v
module light(
  input clk,
  input rst,
  output reg [15:0] led
);
  reg [31:0] count;
  always @(posedge clk) begin
    if (rst) begin led <= 1; count <= 0; end
    else begin
      if (count == 0) led <= {led[14:0], led[15]};
      count <= ((count == 32'd10) ? 32'b0 : count + 1);
    end
  end
  
endmodule

experiment1_light/wave.vcd
$version Generated by VerilatedVcd $end
$date Tue May 30 20:51:39 2023
 $end
$timescale   1ns $end

 $scope module light $end
  $var wire  1 + clk $end
  $var wire 16 ; led [15:0] $end
  $var wire  1 3 rst $end
  $scope module light $end
   $var wire  1 + clk $end
   $var wire 32 # count [31:0] $end
   $var wire 16 ; led [15:0] $end
   $var wire  1 3 rst $end
  $upscope $end
 $upscope $end
$enddefinitions $end


#0
b00000000000000000000000000000000 #
1+
13
b0000000000000000 ;
#1
0+
#2
1+
b0000000000000001 ;
#3
0+
#4
1+
#5
0+
#6
1+
#7
0+
#8
1+
#9
0+
#10
1+
#11
0+
#12
1+
#13
0+
#14
1+
#15
0+
#16
1+
#17
0+
#18
1+
#19
0+
#20
b00000000000000000000000000000001 #
1+
03
b0000000000000010 ;
#21
0+
#22
b00000000000000000000000000000010 #
1+
#23
0+
#24
b00000000000000000000000000000011 #
1+
#25
0+
#26
b00000000000000000000000000000100 #
1+
#27
0+
#28
b00000000000000000000000000000101 #
1+
#29
0+
#30
b00000000000000000000000000000110 #
1+
#31
0+
#32
b00000000000000000000000000000111 #
1+
#33
0+
#34
b00000000000000000000000000001000 #
1+
#35
0+
#36
b00000000000000000000000000001001 #
1+
#37
0+
#38
b00000000000000000000000000001010 #
1+
#39
0+
#40
b00000000000000000000000000001011 #
1+
#41
0+
#42
b00000000000000000000000000001100 #
1+
#43
0+
#44
b00000000000000000000000000001101 #
1+
#45
0+
#46
b00000000000000000000000000001110 #
1+
#47
0+
#48
b00000000000000000000000000001111 #
1+
#49
0+
#50
b00000000000000000000000000010000 #
1+
#51
0+
#52
b00000000000000000000000000010001 #
1+
#53
0+
#54
b00000000000000000000000000010010 #
1+
#55
0+
#56
b00000000000000000000000000010011 #
1+
#57
0+
#58
b00000000000000000000000000010100 #
1+
#59
0+
#60
b00000000000000000000000000010101 #
1+
#61
0+
#62
b00000000000000000000000000010110 #
1+
#63
0+
#64
b00000000000000000000000000010111 #
1+
#65
0+
#66
b00000000000000000000000000011000 #
1+
#67
0+
#68
b00000000000000000000000000011001 #
1+
#69
0+
#70
b00000000000000000000000000011010 #
1+
#71
0+
#72
b00000000000000000000000000011011 #
1+
#73
0+
#74
b00000000000000000000000000011100 #
1+
#75
0+
#76
b00000000000000000000000000011101 #
1+
#77
0+
#78
b00000000000000000000000000011110 #
1+
#79
0+
#80
b00000000000000000000000000011111 #
1+
#81
0+
#82
b00000000000000000000000000100000 #
1+
#83
0+
#84
b00000000000000000000000000100001 #
1+
#85
0+
#86
b00000000000000000000000000100010 #
1+
#87
0+
#88
b00000000000000000000000000100011 #
1+
#89
0+
#90
b00000000000000000000000000100100 #
1+
#91
0+
#92
b00000000000000000000000000100101 #
1+
#93
0+
#94
b00000000000000000000000000100110 #
1+
#95
0+
#96
b00000000000000000000000000100111 #
1+
#97
0+
#98
b00000000000000000000000000101000 #
1+
#99
0+
#100
b00000000000000000000000000101001 #
1+
#101
0+
#102
b00000000000000000000000000101010 #
1+
#103
0+
#104
b00000000000000000000000000101011 #
1+
#105
0+
#106
b00000000000000000000000000101100 #
1+
#107
0+
#108
b00000000000000000000000000101101 #
1+
#109
0+
#110
b00000000000000000000000000101110 #
1+
#111
0+
#112
b00000000000000000000000000101111 #
1+
#113
0+
#114
b00000000000000000000000000110000 #
1+
#115
0+
#116
b00000000000000000000000000110001 #
1+
#117
0+
#118
b00000000000000000000000000110010 #
1+
#119
0+
#120
b00000000000000000000000000110011 #
1+
#121
0+
#122
b00000000000000000000000000110100 #
1+
#123
0+
#124
b00000000000000000000000000110101 #
1+
#125
0+
#126
b00000000000000000000000000110110 #
1+
#127
0+
#128
b00000000000000000000000000110111 #
1+
#129
0+
#130
b00000000000000000000000000111000 #
1+
#131
0+
#132
b00000000000000000000000000111001 #
1+
#133
0+
#134
b00000000000000000000000000111010 #
1+
#135
0+
#136
b00000000000000000000000000111011 #
1+
#137
0+
#138
b00000000000000000000000000111100 #
1+
#139
0+
#140
b00000000000000000000000000111101 #
1+
#141
0+
#142
b00000000000000000000000000111110 #
1+
#143
0+
#144
b00000000000000000000000000111111 #
1+
#145
0+
#146
b00000000000000000000000001000000 #
1+
#147
0+
#148
b00000000000000000000000001000001 #
1+
#149
0+
#150
b00000000000000000000000001000010 #
1+
#151
0+
#152
b00000000000000000000000001000011 #
1+
#153
0+
#154
b00000000000000000000000001000100 #
1+
#155
0+
#156
b00000000000000000000000001000101 #
1+
#157
0+
#158
b00000000000000000000000001000110 #
1+
#159
0+
#160
b00000000000000000000000001000111 #
1+
#161
0+
#162
b00000000000000000000000001001000 #
1+
#163
0+
#164
b00000000000000000000000001001001 #
1+
#165
0+
#166
b00000000000000000000000001001010 #
1+
#167
0+
#168
b00000000000000000000000001001011 #
1+
#169
0+
#170
b00000000000000000000000001001100 #
1+
#171
0+
#172
b00000000000000000000000001001101 #
1+
#173
0+
#174
b00000000000000000000000001001110 #
1+
#175
0+
#176
b00000000000000000000000001001111 #
1+
#177
0+
#178
b00000000000000000000000001010000 #
1+
#179
0+
#180
b00000000000000000000000001010001 #
1+
#181
0+
#182
b00000000000000000000000001010010 #
1+
#183
0+
#184
b00000000000000000000000001010011 #
1+
#185
0+
#186
b00000000000000000000000001010100 #
1+
#187
0+
#188
b00000000000000000000000001010101 #
1+
#189
0+
#190
b00000000000000000000000001010110 #
1+
#191
0+
#192
b00000000000000000000000001010111 #
1+
#193
0+
#194
b00000000000000000000000001011000 #
1+
#195
0+
#196
b00000000000000000000000001011001 #
1+
#197
0+
#198
b00000000000000000000000001011010 #
1+
#199
0+
#200
b00000000000000000000000001011011 #
1+
#201
0+
#202
b00000000000000000000000001011100 #
1+
#203
0+
#204
b00000000000000000000000001011101 #
1+
#205
0+
#206
b00000000000000000000000001011110 #
1+
#207
0+
#208
b00000000000000000000000001011111 #
1+
#209
0+
#210
b00000000000000000000000001100000 #
1+
#211
0+
#212
b00000000000000000000000001100001 #
1+
#213
0+
#214
b00000000000000000000000001100010 #
1+
#215
0+
#216
b00000000000000000000000001100011 #
1+
#217
0+
#218
b00000000000000000000000001100100 #
1+
#219
0+
#220
b00000000000000000000000001100101 #
1+
#221
0+
#222
b00000000000000000000000001100110 #
1+
#223
0+
#224
b00000000000000000000000001100111 #
1+
#225
0+
#226
b00000000000000000000000001101000 #
1+
#227
0+
#228
b00000000000000000000000001101001 #
1+
#229
0+
#230
b00000000000000000000000001101010 #
1+
#231
0+
#232
b00000000000000000000000001101011 #
1+
#233
0+
#234
b00000000000000000000000001101100 #
1+
#235
0+
#236
b00000000000000000000000001101101 #
1+
#237
0+
#238
b00000000000000000000000001101110 #
1+
#239
0+
#240
b00000000000000000000000001101111 #
1+
#241
0+
#242
b00000000000000000000000001110000 #
1+
#243
0+
#244
b00000000000000000000000001110001 #
1+
#245
0+
#246
b00000000000000000000000001110010 #
1+
#247
0+
#248
b00000000000000000000000001110011 #
1+
#249
0+
#250
b00000000000000000000000001110100 #
1+
#251
0+
#252
b00000000000000000000000001110101 #
1+
#253
0+
#254
b00000000000000000000000001110110 #
1+
#255
0+
#256
b00000000000000000000000001110111 #
1+
#257
0+
#258
b00000000000000000000000001111000 #
1+
#259
0+
#260
b00000000000000000000000001111001 #
1+
#261
0+
#262
b00000000000000000000000001111010 #
1+
#263
0+
#264
b00000000000000000000000001111011 #
1+
#265
0+
#266
b00000000000000000000000001111100 #
1+
#267
0+
#268
b00000000000000000000000001111101 #
1+
#269
0+
#270
b00000000000000000000000001111110 #
1+
#271
0+
#272
b00000000000000000000000001111111 #
1+
#273
0+
#274
b00000000000000000000000010000000 #
1+
#275
0+
#276
b00000000000000000000000010000001 #
1+
#277
0+
#278
b00000000000000000000000010000010 #
1+
#279
0+
#280
b00000000000000000000000010000011 #
1+
#281
0+
#282
b00000000000000000000000010000100 #
1+
#283
0+
#284
b00000000000000000000000010000101 #
1+
#285
0+
#286
b00000000000000000000000010000110 #
1+
#287
0+
#288
b00000000000000000000000010000111 #
1+
#289
0+
#290
b00000000000000000000000010001000 #
1+
#291
0+
#292
b00000000000000000000000010001001 #
1+
#293
0+
#294
b00000000000000000000000010001010 #
1+
#295
0+
#296
b00000000000000000000000010001011 #
1+
#297
0+
#298
b00000000000000000000000010001100 #
1+
#299
0+
#300
b00000000000000000000000010001101 #
1+
#301
0+
#302
b00000000000000000000000010001110 #
1+
#303
0+
#304
b00000000000000000000000010001111 #
1+
#305
0+
#306
b00000000000000000000000010010000 #
1+
#307
0+
#308
b00000000000000000000000010010001 #
1+
#309
0+
#310
b00000000000000000000000010010010 #
1+
#311
0+
#312
b00000000000000000000000010010011 #
1+
#313
0+
#314
b00000000000000000000000010010100 #
1+
#315
0+
#316
b00000000000000000000000010010101 #
1+
#317
0+
#318
b00000000000000000000000010010110 #
1+
#319
0+
#320
b00000000000000000000000010010111 #
1+
#321
0+
#322
b00000000000000000000000010011000 #
1+
#323
0+
#324
b00000000000000000000000010011001 #
1+
#325
0+
#326
b00000000000000000000000010011010 #
1+
#327
0+
#328
b00000000000000000000000010011011 #
1+
#329
0+
#330
b00000000000000000000000010011100 #
1+
#331
0+
#332
b00000000000000000000000010011101 #
1+
#333
0+
#334
b00000000000000000000000010011110 #
1+
#335
0+
#336
b00000000000000000000000010011111 #
1+
#337
0+
#338
b00000000000000000000000010100000 #
1+
#339
0+
#340
b00000000000000000000000010100001 #
1+
#341
0+
#342
b00000000000000000000000010100010 #
1+
#343
0+
#344
b00000000000000000000000010100011 #
1+
#345
0+
#346
b00000000000000000000000010100100 #
1+
#347
0+
#348
b00000000000000000000000010100101 #
1+
#349
0+
#350
b00000000000000000000000010100110 #
1+
#351
0+
#352
b00000000000000000000000010100111 #
1+
#353
0+
#354
b00000000000000000000000010101000 #
1+
#355
0+
#356
b00000000000000000000000010101001 #
1+
#357
0+
#358
b00000000000000000000000010101010 #
1+
#359
0+
#360
b00000000000000000000000010101011 #
1+
#361
0+
#362
b00000000000000000000000010101100 #
1+
#363
0+
#364
b00000000000000000000000010101101 #
1+
#365
0+
#366
b00000000000000000000000010101110 #
1+
#367
0+
#368
b00000000000000000000000010101111 #
1+
#369
0+
#370
b00000000000000000000000010110000 #
1+
#371
0+
#372
b00000000000000000000000010110001 #
1+
#373
0+
#374
b00000000000000000000000010110010 #
1+
#375
0+
#376
b00000000000000000000000010110011 #
1+
#377
0+
#378
b00000000000000000000000010110100 #
1+
#379
0+
#380
b00000000000000000000000010110101 #
1+
#381
0+
#382
b00000000000000000000000010110110 #
1+
#383
0+
#384
b00000000000000000000000010110111 #
1+
#385
0+
#386
b00000000000000000000000010111000 #
1+
#387
0+
#388
b00000000000000000000000010111001 #
1+
#389
0+
#390
b00000000000000000000000010111010 #
1+
#391
0+
#392
b00000000000000000000000010111011 #
1+
#393
0+
#394
b00000000000000000000000010111100 #
1+
#395
0+
#396
b00000000000000000000000010111101 #
1+
#397
0+
#398
b00000000000000000000000010111110 #
1+
#399
0+
#400
b00000000000000000000000010111111 #
1+
#401
0+
#402
b00000000000000000000000011000000 #
1+
#403
0+
#404
b00000000000000000000000011000001 #
1+
#405
0+
#406
b00000000000000000000000011000010 #
1+
#407
0+
#408
b00000000000000000000000011000011 #
1+
#409
0+
#410
b00000000000000000000000011000100 #
1+
#411
0+
#412
b00000000000000000000000011000101 #
1+
#413
0+
#414
b00000000000000000000000011000110 #
1+
#415
0+
#416
b00000000000000000000000011000111 #
1+
#417
0+
#418
b00000000000000000000000011001000 #
1+
#419
0+
#420
b00000000000000000000000011001001 #
1+
#421
0+
#422
b00000000000000000000000011001010 #
1+
#423
0+
#424
b00000000000000000000000011001011 #
1+
#425
0+
#426
b00000000000000000000000011001100 #
1+
#427
0+
#428
b00000000000000000000000011001101 #
1+
#429
0+
#430
b00000000000000000000000011001110 #
1+
#431
0+
#432
b00000000000000000000000011001111 #
1+
#433
0+
#434
b00000000000000000000000011010000 #
1+
#435
0+
#436
b00000000000000000000000011010001 #
1+
#437
0+
#438
b00000000000000000000000011010010 #
1+
#439
0+
#440
b00000000000000000000000011010011 #
1+
#441
0+
#442
b00000000000000000000000011010100 #
1+
#443
0+
#444
b00000000000000000000000011010101 #
1+
#445
0+
#446
b00000000000000000000000011010110 #
1+
#447
0+
#448
b00000000000000000000000011010111 #
1+
#449
0+
#450
b00000000000000000000000011011000 #
1+
#451
0+
#452
b00000000000000000000000011011001 #
1+
#453
0+
#454
b00000000000000000000000011011010 #
1+
#455
0+
#456
b00000000000000000000000011011011 #
1+
#457
0+
#458
b00000000000000000000000011011100 #
1+
#459
0+
#460
b00000000000000000000000011011101 #
1+
#461
0+
#462
b00000000000000000000000011011110 #
1+
#463
0+
#464
b00000000000000000000000011011111 #
1+
#465
0+
#466
b00000000000000000000000011100000 #
1+
#467
0+
#468
b00000000000000000000000011100001 #
1+
#469
0+
#470
b00000000000000000000000011100010 #
1+
#471
0+
#472
b00000000000000000000000011100011 #
1+
#473
0+
#474
b00000000000000000000000011100100 #
1+
#475
0+
#476
b00000000000000000000000011100101 #
1+
#477
0+
#478
b00000000000000000000000011100110 #
1+
#479
0+
#480
b00000000000000000000000011100111 #
1+
#481
0+
#482
b00000000000000000000000011101000 #
1+
#483
0+
#484
b00000000000000000000000011101001 #
1+
#485
0+
#486
b00000000000000000000000011101010 #
1+
#487
0+
#488
b00000000000000000000000011101011 #
1+
#489
0+
#490
b00000000000000000000000011101100 #
1+
#491
0+
#492
b00000000000000000000000011101101 #
1+
#493
0+
#494
b00000000000000000000000011101110 #
1+
#495
0+
#496
b00000000000000000000000011101111 #
1+
#497
0+
#498
b00000000000000000000000011110000 #
1+
